groupdocs_rewriter_cloud/__init__.py
groupdocs_rewriter_cloud/api_client.py
groupdocs_rewriter_cloud/api_response.py
groupdocs_rewriter_cloud/configuration.py
groupdocs_rewriter_cloud/exceptions.py
groupdocs_rewriter_cloud/py.typed
groupdocs_rewriter_cloud/rest.py
groupdocs_rewriter_cloud/api/__init__.py
groupdocs_rewriter_cloud/api/compare_api.py
groupdocs_rewriter_cloud/api/detect_api.py
groupdocs_rewriter_cloud/api/estimate_api.py
groupdocs_rewriter_cloud/api/file_api.py
groupdocs_rewriter_cloud/api/formalize_api.py
groupdocs_rewriter_cloud/api/generate_api.py
groupdocs_rewriter_cloud/api/info_api.py
groupdocs_rewriter_cloud/api/paraphrase_api.py
groupdocs_rewriter_cloud/api/simplify_api.py
groupdocs_rewriter_cloud/api/summarize_api.py
groupdocs_rewriter_cloud/api/swagger_api.py
groupdocs_rewriter_cloud/api/synonymize_api.py
groupdocs_rewriter_cloud/models/__init__.py
groupdocs_rewriter_cloud/models/base_text_request.py
groupdocs_rewriter_cloud/models/cloud_text_request.py
groupdocs_rewriter_cloud/models/compare_text_request.py
groupdocs_rewriter_cloud/models/compare_text_response.py
groupdocs_rewriter_cloud/models/degree_enum.py
groupdocs_rewriter_cloud/models/detection_file_request.py
groupdocs_rewriter_cloud/models/detection_file_response.py
groupdocs_rewriter_cloud/models/detection_ocr_request.py
groupdocs_rewriter_cloud/models/detection_supported_formats.py
groupdocs_rewriter_cloud/models/detection_text_request.py
groupdocs_rewriter_cloud/models/detection_text_response.py
groupdocs_rewriter_cloud/models/detection_trial_file_request.py
groupdocs_rewriter_cloud/models/estimate_request.py
groupdocs_rewriter_cloud/models/estimate_response.py
groupdocs_rewriter_cloud/models/file_saving_mode.py
groupdocs_rewriter_cloud/models/formalize_file_request.py
groupdocs_rewriter_cloud/models/formalize_file_response.py
groupdocs_rewriter_cloud/models/formalize_ocr_request.py
groupdocs_rewriter_cloud/models/formalize_supported_fromats.py
groupdocs_rewriter_cloud-25.7.0.dist-info/LICENSE
groupdocs_rewriter_cloud-25.7.0.dist-info/METADATA
groupdocs_rewriter_cloud-25.7.0.dist-info/WHEEL
groupdocs_rewriter_cloud-25.7.0.dist-info/top_level.txt
groupdocs_rewriter_cloud-25.7.0.dist-info/RECORD
