Metadata-Version: 2.1
Name: groupdocs-rewriter-cloud
Version: 25.7.0
Summary: GroupDocs.Rewriter API
Home-page: https://github.com/groupdocs-rewriter-cloud/groupdocs-rewriter-cloud-python
Author: GroupDocs
Author-email: anton.perhunov@aspose.com
License: MIT
Keywords: GroupDocs.Rewriter Cloud API Reference,Aspose,GroupDocs,RewriterRewriter Cloud,GroupDocs.Rewriter API
Classifier: Development Status :: 5 - Production/Stable
Classifier: Intended Audience :: Developers
Classifier: Topic :: Software Development :: Libraries :: Python Modules
Classifier: License :: OSI Approved :: MIT License
Classifier: Programming Language :: Python :: 3.7
Classifier: Programming Language :: Python :: 3.8
Classifier: Programming Language :: Python :: 3.9
Classifier: Programming Language :: Python :: 3.10
License-File: LICENSE
Requires-Dist: urllib3>=1.25.3
Requires-Dist: python-dateutil
Requires-Dist: pydantic<2,>=1.10.5
Requires-Dist: aenum
Requires-Dist: oauthlib~=3.2.2
Requires-Dist: requests-oauthlib~=1.3.1
